<?xml version="1.0" encoding="utf-8" ?>
<dwsync>
<file name="account.entity.php" server="C:/Users/ADMIN/Desktop/MusicWebProject-GroupHxH" local="132658781679630235" remote="132658781670000000" Dst="0" />
<file name="account.model.php" server="C:/Users/ADMIN/Desktop/MusicWebProject-GroupHxH" local="132664112186101489" remote="132664112180000000" Dst="0" />
<file name="mv.model.php" server="D:/BAIGIANG/Web programming/WebProject/" local="132671635347050874" remote="132671635340000000" Dst="0" />
<file name="song.model.php" server="D:/BAIGIANG/Web programming/WebProject/" local="132671639556575233" remote="132671639550000000" Dst="0" />
<file name="song.entity.php" server="D:/BAIGIANG/Web programming/WebProject/" local="132671200468362914" remote="132671200460000000" Dst="0" />
<file name="mv.entity.php" server="D:/BAIGIANG/Web programming/WebProject/" local="132665150019762921" remote="132665150010000000" Dst="0" />
<file name="singer.entity.php" server="D:/BAIGIANG/Web programming/WebProject/" local="132671790134160903" remote="132671790130000000" Dst="0" />
<file name="singer.model.php" server="D:/BAIGIANG/Web programming/WebProject/" local="132671793591668749" remote="132671793590000000" Dst="0" />
</dwsync>